{
  "templates": {
    "type": "JSON",
    "content": [
      {
        "id": "145267443",
        "Flight": "WS2707",
        "PickupDate": "2026-01-17",
        "PickupTime": "10:30",
        "HotelName": "Hotel Vista Sol Punta Cana",
        "HotelNumber": 13633
      },
      {
        "id": "144853443",
        "Flight": "WS2883",
        "PickupDate": "2026-01-17",
        "PickupTime": "10:40",
        "HotelName": "Hotel Vista Sol Punta Cana",
        "HotelNumber": 13633
      },
      {
        "id": "146487763",
        "Flight": "WS2903",
        "PickupDate": "2026-01-17",
        "PickupTime": "12:00",
        "HotelName": "Hotel Vista Sol Punta Cana",
        "HotelNumber": 13633
      },
      {
        "id": "924QG2",
        "Flight": "G47001",
        "PickupDate": "2026-01-17",
        "PickupTime": "09:50",
        "HotelName": "Hotel Vista Sol Punta Cana",
        "HotelNumber": 13633
      },
      {
        "id": "144853173",
        "Flight": "WS2883",
        "PickupDate": "2026-01-17",
        "PickupTime": "10:40",
        "HotelName": "Hotel Vista Sol Punta Cana",
        "HotelNumber": 13633
      },
      {
        "id": "149548332",
        "Flight": "WS2903",
        "PickupDate": "2026-01-17",
        "PickupTime": "12:00",
        "HotelName": "Hotel Vista Sol Punta Cana",
        "HotelNumber": 13633
      },
      {
        "id": "146487773",
        "Flight": "WS2903",
        "PickupDate": "2026-01-17",
        "PickupTime": "12:00",
        "HotelName": "Hotel Vista Sol Punta Cana",
        "HotelNumber": 13633
      },
      {
        "id": "146591963",
        "Flight": "WS2903",
        "PickupDate": "2026-01-17",
        "PickupTime": "12:00",
        "HotelName": "Hotel Vista Sol Punta Cana",
        "HotelNumber": 13633
      },
      {
        "id": "144853313",
        "Flight": "WS2883",
        "PickupDate": "2026-01-17",
        "PickupTime": "10:40",
        "HotelName": "Hotel Vista Sol Punta Cana",
        "HotelNumber": 13633
      },
      {
        "id": "148166693",
        "Flight": "WS2913",
        "PickupDate": "2026-01-17",
        "PickupTime": "12:45",
        "HotelName": "Hotel Vista Sol Punta Cana",
        "HotelNumber": 13633
      },
      {
        "id": "150064473",
        "Flight": "WS2903",
        "PickupDate": "2026-01-17",
        "PickupTime": "12:00",
        "HotelName": "Hotel Vista Sol Punta Cana",
        "HotelNumber": 13633
      },
      {
        "id": "144728273",
        "Flight": "WS2903",
        "PickupDate": "2026-01-17",
        "PickupTime": "12:00",
        "HotelName": "Hotel Vista Sol Punta Cana",
        "HotelNumber": 13633
      },
      {
        "id": "144885303",
        "Flight": "WS2707",
        "PickupDate": "2026-01-17",
        "PickupTime": "10:30",
        "HotelName": "Hotel Vista Sol Punta Cana",
        "HotelNumber": 13633
      },
      {
        "id": "146487783",
        "Flight": "WS2903",
        "PickupDate": "2026-01-17",
        "PickupTime": "12:00",
        "HotelName": "Hotel Vista Sol Punta Cana",
        "HotelNumber": 13633
      },
      {
        "id": "461-2739066",
        "Flight": "CM749",
        "PickupDate": "2026-01-17",
        "PickupTime": "14:20",
        "HotelName": "Hotel Vista Sol Punta Cana",
        "HotelNumber": 13633
      },
      {
        "id": "Z1G6TT",
        "Flight": "LA0591",
        "PickupDate": "2026-01-17",
        "PickupTime": "09:30",
        "HotelName": "Hotel Vista Sol Punta Cana",
        "HotelNumber": 13633
      },
      {
        "id": "150152313",
        "Flight": "WS2903",
        "PickupDate": "2026-01-17",
        "PickupTime": "12:00",
        "HotelName": "Hotel Vista Sol Punta Cana",
        "HotelNumber": 13633
      }
    ],
    "source": {
      "data_source": "Google Sheets (Private)",
      "update_frequency": "Automated"
    }
  }
}