{
  "templates": {
    "type": "JSON",
    "content": [
      {
        "id": "145359043",
        "Flight": "WS2913",
        "PickupDate": "2026-01-16",
        "PickupTime": "12:45",
        "HotelName": "Hotel Vista Sol Punta Cana",
        "HotelNumber": 13633
      },
      {
        "id": "146111723",
        "Flight": "WS2655",
        "PickupDate": "2026-01-16",
        "PickupTime": "07:00",
        "HotelName": "Hotel Vista Sol Punta Cana",
        "HotelNumber": 13633
      },
      {
        "id": "148233602",
        "Flight": "WS2743",
        "PickupDate": "2026-01-16",
        "PickupTime": "15:40",
        "HotelName": "Hotel Vista Sol Punta Cana",
        "HotelNumber": 13633
      },
      {
        "id": "147084653",
        "Flight": "WS2913",
        "PickupDate": "2026-01-16",
        "PickupTime": "12:45",
        "HotelName": "Hotel Vista Sol Punta Cana",
        "HotelNumber": 13633
      },
      {
        "id": "144993002",
        "Flight": "WS2903",
        "PickupDate": "2026-01-16",
        "PickupTime": "11:10",
        "HotelName": "Hotel Vista Sol Punta Cana",
        "HotelNumber": 13633
      },
      {
        "id": "150058983",
        "Flight": "WS2903",
        "PickupDate": "2026-01-16",
        "PickupTime": "11:10",
        "HotelName": "Hotel Vista Sol Punta Cana",
        "HotelNumber": 13633
      },
      {
        "id": "Q46V3N",
        "Flight": "AV0129",
        "PickupDate": "2026-01-16",
        "PickupTime": "09:00",
        "HotelName": "Hotel Vista Sol Punta Cana",
        "HotelNumber": 13633
      },
      {
        "id": "147084683",
        "Flight": "WS2913",
        "PickupDate": "2026-01-16",
        "PickupTime": "12:45",
        "HotelName": "Hotel Vista Sol Punta Cana",
        "HotelNumber": 13633
      },
      {
        "id": "149620643",
        "Flight": "WS2913",
        "PickupDate": "2026-01-16",
        "PickupTime": "12:45",
        "HotelName": "Hotel Vista Sol Punta Cana",
        "HotelNumber": 13633
      }
    ],
    "source": {
      "data_source": "Google Sheets (Private)",
      "update_frequency": "Automated"
    }
  }
}